<screenset>
	<screen number="1" escapeScreen="1">
		<line>You are facing <monsters /></line>
		<line />
		<line>Will the party</line>
		<can option="advance"><choice keys="aA" action="advance" screen="3">Advance,</choice></can>
		<choice keys="fF" action="combatOption" screen="2">Fight or</choice>
		<choice keys="rR" action="runAway" screen="3">Run</choice>
	</screen>
	<screen number="2" escapeScreen="2">
		<line>Select battle option for <name /></line>
		<line />
		<can option="attack"><choice keys="aA" action="attack" screen="3">Attack foes</choice></can>
		<choice keys="pP" action="partyAttack" screen="3">Party attack</choice>
		<choice keys="dD" action="defend" screen="3">Defend</choice>
		<choice keys="uU" action="useItem" screen="3">Use an item</choice>
	</screen>
	<combat number="3" escapeScreen="0" timeout="1000">
	</combat>
	<screen number="4" escapeScreen="-1">
		<line>You have won! Each character receives <xp /> experience points for valor and battle knowledge, and gains <gold /> pieces of gold.</line>
	</screen>
	<screen number="5" escapeScreen="5">
		<line>Do you wish to enter a round of intra party combat?</line>
		<choice keys="yY" action="combatOption" screen="2">Yes, or</choice>
		<choice keys="nN" screen="-1">No</choice>
	</screen>
	<error type="runAway">You are attempting to run away.
You manage to get away!</error>
</screenset>
